{
	"instance" : {
		"zIndex:" : null,
		"showInNavigator:" : null,
		"threshold:" : null,
		"compareBase:" : null,
		"borderWidth:" : null,
		"data" : null,
		"gapUnit:" : null,
		"stacking:" : null,
		"animation" : null,
		"dashStyle:" : null,
		"connectNulls:" : null,
		"zones" : null,
		"tileShape:" : null,
		"dataGrouping" : null,
		"colsize:" : null,
		"rowsize:" : null,
		"xAxis:" : null,
		"nullColor:" : null,
		"compare:" : null,
		"yAxis:" : null,
		"step:" : null,
		"lineWidth:" : null,
		"states:" : null,
		"negativeColor:" : null,
		"exposeElementToA11y:" : null,
		"states" : null,
		"stack:" : null,
		"gapSize:" : null,
		"pointPadding:" : null,
		"dataLabels" : null,
		"point" : null,
		"findNearestPointBy:" : null,
		"showInLegend:" : null,
		"colorIndex:" : null,
		"getExtremesFromAll:" : null,
		"softThreshold:" : null,
		"skipKeyboardNavigation:" : null,
		"pointStart:" : null,
		"keys:" : null,
		"name:" : null,
		"linecap:" : null,
		"stickyTracking:" : null,
		"pointPlacement:" : null,
		"turboThreshold:" : null,
		"animationLimit:" : null,
		"cropThreshold:" : null,
		"pointRange:" : null,
		"compareStart:" : null,
		"pointDescriptionFormatter:" : null,
		"allowPointSelect:" : null,
		"description:" : null,
		"events:" : null,
		"className:" : null,
		"legendIndex:" : null,
		"index:" : null,
		"pointInterval:" : null,
		"label" : null,
		"zoneAxis:" : null,
		"linkedTo:" : null,
		"showCheckbox:" : null,
		"events" : null,
		"boostThreshold:" : null,
		"visible:" : null,
		"tooltip" : null,
		"color:" : null,
		"connectEnds:" : null,
		"marker" : null,
		"pointIntervalUnit:" : null,
		"initialize" : null,
		"selected:" : null,
		"id:" : null,
		"enableMouseTracking:" : null,
		"cursor:" : null,
		"navigatorOptions:" : null,
		"type:" : null,
		"data:" : null
	},
	"class" : { }
}