{
	"instance" : {
		"events" : null,
		"groupZPadding:" : null,
		"grouping:" : null,
		"enableMouseTracking:" : null,
		"className:" : null,
		"joinBy:" : null,
		"borderWidth:" : null,
		"pointPadding:" : null,
		"pointDescriptionFormatter:" : null,
		"edgeColor:" : null,
		"pointStart:" : null,
		"threshold:" : null,
		"stickyTracking:" : null,
		"zIndex:" : null,
		"crisp:" : null,
		"groupPadding:" : null,
		"zones" : null,
		"color:" : null,
		"negativeColor:" : null,
		"depth:" : null,
		"keys:" : null,
		"maxPointWidth:" : null,
		"pointWidth:" : null,
		"softThreshold:" : null,
		"colorByPoint:" : null,
		"cursor:" : null,
		"getExtremesFromAll:" : null,
		"vectorLength:" : null,
		"findNearestPointBy:" : null,
		"pointInterval:" : null,
		"selected:" : null,
		"allowPointSelect:" : null,
		"showCheckbox:" : null,
		"lineWidth:" : null,
		"colors:" : null,
		"animation" : null,
		"minPointLength:" : null,
		"allAreas:" : null,
		"borderColor:" : null,
		"onSeries:" : null,
		"colorAxis:" : null,
		"label" : null,
		"pointPlacement:" : null,
		"showInLegend:" : null,
		"animationLimit:" : null,
		"states:" : null,
		"turboThreshold:" : null,
		"yOffset:" : null,
		"skipKeyboardNavigation:" : null,
		"point" : null,
		"states" : null,
		"borderRadius:" : null,
		"edgeWidth:" : null,
		"description:" : null,
		"visible:" : null,
		"exposeElementToA11y:" : null,
		"pointRange:" : null,
		"colorIndex:" : null,
		"tooltip" : null,
		"events:" : null,
		"dataLabels" : null,
		"linkedTo:" : null,
		"pointIntervalUnit:" : null,
		"zoneAxis:" : null
	},
	"class" : { }
}