{
	"instance" : {
		"testUseHTML" : "MarianoMartinezPeck 1/11/2017 12:41",
		"testItemHiddenStyle" : "MarianoMartinezPeck 1/11/2017 12:41",
		"testSymbolPadding" : "MarianoMartinezPeck 1/11/2017 12:41",
		"testSymbolRadius" : "MarianoMartinezPeck 1/11/2017 12:41",
		"testItemHoverStyle" : "MarianoMartinezPeck 1/11/2017 12:41",
		"testEnabled" : "MarianoMartinezPeck 1/11/2017 12:41",
		"testMargin" : "MarianoMartinezPeck 1/11/2017 12:41",
		"testBackgroundColor" : "MarianoMartinezPeck 1/11/2017 12:41",
		"testAlign" : "MarianoMartinezPeck 1/11/2017 12:41",
		"testTitle" : "MarianoMartinezPeck 1/11/2017 12:41",
		"testPadding" : "MarianoMartinezPeck 1/11/2017 12:41",
		"testFloating" : "MarianoMartinezPeck 1/11/2017 12:41",
		"testBorderRadius" : "MarianoMartinezPeck 1/11/2017 12:41",
		"testReversed" : "MarianoMartinezPeck 1/11/2017 12:41",
		"testItemDistance" : "MarianoMartinezPeck 1/11/2017 12:41",
		"testWidth" : "MarianoMartinezPeck 1/11/2017 12:41",
		"testSymbolWidth" : "MarianoMartinezPeck 1/11/2017 12:41",
		"testX" : "MarianoMartinezPeck 1/11/2017 12:41",
		"testMaxHeight" : "MarianoMartinezPeck 1/11/2017 12:41",
		"testItemStyle" : "MarianoMartinezPeck 1/11/2017 12:41",
		"testItemMarginTop" : "MarianoMartinezPeck 1/11/2017 12:41",
		"testShadow" : "MarianoMartinezPeck 1/11/2017 12:41",
		"testLabelFormatter" : "MarianoMartinezPeck 1/11/2017 12:41",
		"testLayout" : "MarianoMartinezPeck 1/11/2017 12:41",
		"testStyle" : "MarianoMartinezPeck 1/11/2017 12:41",
		"testY" : "MarianoMartinezPeck 1/11/2017 12:41",
		"testBorderColor" : "MarianoMartinezPeck 1/11/2017 12:41",
		"testLabelFormat" : "MarianoMartinezPeck 1/11/2017 12:41",
		"testSquareSymbol" : "MarianoMartinezPeck 1/11/2017 12:41",
		"testItemMarginBottom" : "MarianoMartinezPeck 1/11/2017 12:41",
		"testSymbolHeight" : "MarianoMartinezPeck 1/11/2017 12:41",
		"testVerticalAlign" : "MarianoMartinezPeck 1/11/2017 12:41",
		"testItemWidth" : "MarianoMartinezPeck 1/11/2017 12:41",
		"testBorderWidth" : "MarianoMartinezPeck 1/11/2017 12:41"
	},
	"class" : { }
}